README.md
setup.cfg
setup.py
amazon_pay/__init__.py
amazon_pay/ap_region.py
amazon_pay/client.py
amazon_pay/ipn_handler.py
amazon_pay/login_with_amazon.py
amazon_pay/lwa_region.py
amazon_pay/payment_request.py
amazon_pay/payment_response.py
amazon_pay/version.py
amazon_pay.egg-info/PKG-INFO
amazon_pay.egg-info/SOURCES.txt
amazon_pay.egg-info/dependency_links.txt
amazon_pay.egg-info/requires.txt
amazon_pay.egg-info/top_level.txt
test/test_ap.py
test/test_ipn.py
test/test_lwa.py